playlight/__init__.py
playlight/demo.py
playlight/playlight.py
playlight-0.6.dist-info/LICENSE
playlight-0.6.dist-info/METADATA
playlight-0.6.dist-info/WHEEL
playlight-0.6.dist-info/top_level.txt
playlight-0.6.dist-info/RECORD
